Metadata-Version: 2.4
Name: adafruit-circuitpython-ssd1331
Version: 2.0.2
Summary: displayio driver for SSD1331 TFT-LCD displays.
Author-email: Adafruit Industries <circuitpython@adafruit.com>
License: MIT
Project-URL: Homepage, https://github.com/adafruit/Adafruit_CircuitPython_SSD1331
Keywords: adafruit,blinka,circuitpython,micropython,ssd1331,display,tft,lcd,displayio
Classifier: Intended Audience :: Developers
Classifier: Topic :: Software Development :: Libraries
Classifier: Topic :: Software Development :: Embedded Systems
Classifier: Topic :: System :: Hardware
Classifier: License :: OSI Approved :: MIT License
Classifier: Programming Language :: Python :: 3
License-File: LICENSE
Requires-Dist: Adafruit-Blinka
Requires-Dist: adafruit-blinka-displayio
Provides-Extra: optional
Dynamic: license-file
